trommel/core.py
trommel-0.1.7.dist-info/METADATA
trommel-0.1.7.dist-info/WHEEL
trommel-0.1.7.dist-info/licenses/LICENSE
trommel-0.1.7.dist-info/RECORD
