Metadata-Version: 2.4
Name: trommel
Version: 0.1.7
Summary: Data cleaning functions and pipelines for morphological profiles.
Author: Alan Munoz
License-File: LICENSE
Requires-Python: <3.12,>=3.10
Requires-Dist: duckdb>=1.1.3
Requires-Dist: numpy>=1.18.2
Requires-Dist: polars>=1.16.0
Requires-Dist: pyarrow>=18.1.0
Provides-Extra: dev
Requires-Dist: ruff; extra == 'dev'
